a6 - IO Peripheral/biu.v
`timescale 1ns/1ps
// Bus interface unit: assumes two branches of the bus -
// 1. connect to dmem
// 2. connect to a single peripheral
// The BIU needs to know the addresses at which DMEM and peripheral are
// connected, so it can do the required multiplexing. 
// These need to be added as part of your code. 
module biu (
    input clk,
    input reset,
    input [31:0] daddr,
    input [31:0] dwdata,
    input [3:0] dwe,
    output [31:0] drdata,

    //Signals going to/from dmem
    output [31:0] daddr1,
    output [31:0] dwdata1,
    output [3:0]  dwe1,
    input  [31:0] drdata1,

    //Signals going to/from peripheral
    output [31:0] daddr2,
    output [31:0] dwdata2,
    output [3:0]  dwe2,
    input  [31:0] drdata2
);
    
    //DMEM needs 4K locations (16KB memory). So only lower 14 bits (12 for 4K locations, last 2 ignored) of the address bus are used
    //So, map the peripheral to the remaining unallotted memory
    //Use the upper 18 bits of addr bus as select line for peripheral or dmem

    assign drdata = (daddr[31:14] == 0) ?  drdata1 : drdata2;
    assign dwe1 = (daddr[31:14] == 0) ? dwe : 0;
    assign dwe2 = (daddr[31:14] !== 0) ? dwe : 0;

    // Send values to DMEM or peripheral (or both if it does not matter) as required

    assign daddr1 = daddr;
    assign dwdata1 = dwdata;

    assign daddr2 = daddr;
    assign dwdata2 = dwdata;

endmodule

a6 - IO Peripheral/outperiph.v
`timescale 1ns/1ps
`define OUTFILE "output.txt"

module outperiph (
    input clk,
    input reset,
    input [31:0] daddr,
    input [31:0] dwdata,
    input [3:0] dwe,
    output [31:0] drdata
);

    reg [31:0] drdata;
    integer out_file;
    
    // Implement the peripheral logic here: use $fwrite to the file output.txt
    // Use the `define above to open the file so that it can be 
    // overridden later if needed

    // Return value from here (if requested based on address) should
    // be the number of values written so far

    //Preset counter value to 0
    //Open file `OUTFILE for writing data
    initial begin 
        drdata = 0;  
        out_file = $fopen(`OUTFILE,"w");  
    end
    
    always @(posedge clk) begin
        if (reset) begin        //Make counter to 0 whenever reset occurs
            drdata = 0;
        end else begin
            if (dwe) begin      //When dwe on : Sync write of dwdata (char) into `OUTFILE and increment counter
                $fwrite(out_file,"%c",dwdata);
                drdata = drdata + 1;
            end
        end
    end
    
endmodule

a6 - IO Peripheral/dmem.v
`timescale 1ns/1ps
`define DMEM_N_FILE(x,y) {x,y,".mem"}
`define MEMTOP 4095

module dmem (
    input clk,
    input [31:0] daddr,
    input [31:0] dwdata,
    input [3:0] dwe,
    output [31:0] drdata
);
    // 4K location, 16KB total, split in 4 banks
    reg [7:0] mem0[0:`MEMTOP];  
    reg [7:0] mem1[0:`MEMTOP];  
    reg [7:0] mem2[0:`MEMTOP];  
    reg [7:0] mem3[0:`MEMTOP];  
    reg [31:0] memt[0:`MEMTOP]; // temp to read

    wire [29:0] a;
    integer i;

    initial begin 
        $readmemh({`TESTDIR,"/idata.mem"}, memt); 
        for (i=0; i<2372; i=i+1) begin
            mem0[i] = memt[i][ 7: 0];
            mem1[i] = memt[i][15: 8];
            mem2[i] = memt[i][23:16];
            mem3[i] = memt[i][31:24];
        end
    end

    assign a = daddr[31:2];
    
    // Selecting bytes to be done inside CPU
    assign drdata = { mem3[a], mem2[a], mem1[a], mem0[a]};  

    always @(posedge clk) begin
        if (dwe[3]) mem3[a] = dwdata[31:24];
        if (dwe[2]) mem2[a] = dwdata[23:16];
        if (dwe[1]) mem1[a] = dwdata[15: 8];
        if (dwe[0]) mem0[a] = dwdata[ 7: 0];
    end


endmodule

a7 - Synthesis/imem.v
`timescale 1ns/1ps

module imem (
    input [31:0] iaddr,
    output [31:0] idata
);
    // Ignores LSB 2 bits, so will not generate alignment exception
    reg [31:0] mem[0:4095]; // Define a 4-K location memory (16KB)
    initial begin $readmemh("idata.mem",mem); end

    assign idata = mem[iaddr[31:2]];
endmodule

a6 - IO Peripheral/regfile.v
module regfile(
    input [4:0] rs1,     // Source reg 1
    input [4:0] rs2,     // Source reg 2
    input [4:0] rs3,     // Source reg 3
    input [4:0] rd,      // Dest reg
    input we,            // should write update occur
    input [31:0] wdata,  // value to be written
    output [31:0] rv1,   // First read value
    output [31:0] rv2,   // Second read value
    output [31:0] rv3,   // Third read value
    input clk            // Clock signal
);

    reg [31:0] memory [31:0]; // 32 32-bit registers in memory
    integer i;

   //preset internal register values to 0
    initial begin
        for(i=0; i<32; i=i+1) begin
            memory[i] = 32'b0;
        end
    end

    //combinational read block
    assign rv1 = memory[rs1];   //value in register 1 
    assign rv2 = memory[rs2];   //value in register 2
    assign rv3 = memory[rs3];   //value in register 3

    //synchronous write (w.r.t clk) block
    always @(posedge clk) begin
        if (we & rd !== 0) 
            memory[rd] <= wdata;
    end

endmodule

a6 - IO Peripheral/alu32.v
module alu32(
    input [5:0] op,      // some input encoding of your choice
    input [31:0] rv1,    // First operand
    input [31:0] rv2,    // Second operand
    output [31:0] rvout  // Output value
);
    reg [31:0] alu_out;

    //Combinational block to compute ALU ops
    assign rvout = alu_out;

    always @(*) begin
        case (op)
            6'd0    :   alu_out = 0;
            6'd1    :   alu_out = rv1 + rv2;                                  //ADD
            6'd2    :   alu_out = rv1 + (~rv2) + 1;                           //SUB
            6'd3    :   alu_out = rv1 & rv2;                                  //AND
            6'd4    :   alu_out = rv1 | rv2;                                  //OR
            6'd5    :   alu_out = rv1 ^ rv2;                                  //XOR
            6'd6    :   alu_out = (rv1 < rv2) ? 1 : 0;                        //SLT  (Set Less Than)
            6'd7    :   alu_out = ($unsigned(rv1) < $unsigned(rv2)) ? 1 : 0;  //SLTU (Set Less Than Unsigned)
            6'd8    :   alu_out = rv1 << rv2;                                 //SLL  (Shift Left Logical)
            6'd9    :   alu_out = rv1 >> rv2;                                 //SRL  (Shift Right Logical)
            6'd10   :   alu_out = rv1 >>> rv2;                                //SRA  (Shift Right Arithmetic)                                            
            default :   alu_out = 1'bx;                                       //Invalid
        endcase
    end

endmodule

a6 - IO Peripheral/cpu.v
module cpu (
    input clk, 
    input reset,
    output [31:0] iaddr,
    input [31:0] idata,
    output [31:0] daddr,
    input [31:0] drdata,
    output [31:0] dwdata,
    output [3:0] dwe
);
    //Given input/outputs
    reg [31:0] iaddr;   

    //Standard parts in idata
    wire [11:0] immediate;  
    wire [6:0] opcode;
    wire [2:0] func3;
    wire [4:0] rs1, rs2, rd;

    //CPU specific variables
    reg [4:0] opflag;

    //ALU specific variables
    wire [31:0] alu_in1, alu_in2, alu_out;  
    reg [5:0] alu_opcode;   
    wire [11:0] alu_imm; 

    //Load/Store specific variables
    wire [11:0] s_offset, m_offset;
    wire [4:0] mem_addr;
    wire [31:0] u_immediate;

    //Buffers for bytes/half-words
    wire [31:0] buff_in;
    reg [31:0]  buff_out;

    //Branch specific variables
    wire [31:0] b_offset, b_imm;
    wire [31:0] j_offset;
    wire [31:0] j_dest;
    wire [31:0] iaddr_new;

    //32 32-bit registers in memory
    wire [31:0] rv1, rv2, rv3; 
    wire [31:0] reg_data;
    wire [4:0] reg_dest;
    wire reg_we;

    alu32 i1(             //combinational ALU block
        .op(alu_opcode),
        .rv1(alu_in1),  
        .rv2(alu_in2),
        .rvout(alu_out)
    );

    regfile i2(          //32-bit internal registers with combinational read blocks and sync write block
        .clk(clk),
        .rs1(rs1),
        .rs2(rs2),
        .rs3(mem_addr),
        .rv1(rv1),
        .rv2(rv2),
        .rv3(rv3),
        .rd(reg_dest),
        .we(reg_we & !reset),
        .wdata(reg_data)
    );

    initial begin   //Preset all opcodes to 0
        opflag = 0;
        alu_opcode = 0;
    end

    /*--------------------------------------------------------------------------------------------------------------------*/

    //Program Counter
    always @(posedge clk) begin
        if (reset) begin
            iaddr = 0;
        end else begin 
            iaddr = iaddr_new;   //Handles branching/jump ops
        end
    end

    /*--------------------------------------------------------------------------------------------------------------------*/

    //Decoding instruction
    assign immediate = idata[31:20]; //Immediate value
    assign rs2 = idata[24:20];       //Source register 2
    assign rs1 = idata[19:15];       //Source register 1
    assign func3 = idata[14:12];     //Sub func code
    assign rd = idata[11:7];         //Destination register
    assign opcode = idata[6:0];      //Opcode

    always @(opcode) begin
        case (opcode[6:0])
            7'b0110011:   opflag = 1;   //ALU_ops_reg
            7'b0010011:   opflag = 2;   //ALU_ops_imm
            7'b1100011:   opflag = 3;   //Branch_ops 
            7'b0110111:   opflag = 4;   //LUI
            7'b0010111:   opflag = 5;   //AUIPC
            7'b1101111:   opflag = 6;   //JAL
            7'b1100111:   opflag = 7;   //JALR
            7'b0000011:   opflag = 8;   //Load_ops
            7'b0100011:   opflag = 9;   //Store_ops
            default:      opflag = 0;   //Invalid
        endcase
    end

    /*--------------------------------------------------------------------------------------------------------------------*/

    //Branches
    assign b_imm = {{21{idata[31]}},idata[7],idata[30:25],idata[11:8]} << 1;
    assign b_offset = (func3 == 3'b000 & rv1 == rv2) ? b_imm :                          //BEQ
                      (func3 == 3'b001 & rv1 != rv2) ? b_imm :                          //BNE
                      (func3 == 3'b100 & rv1 < rv2) ? b_imm :                           //BLT
                      (func3 == 3'b101 & rv1 >= rv2) ? b_imm :                          //BGE
                      (func3 == 3'b110 & $unsigned(rv1) < $unsigned(rv2)) ? b_imm :     //BLTU
                      (func3 == 3'b111 & $unsigned(rv1) >= $unsigned(rv2)) ? b_imm : 4; //BGEU

    //Unconditional Jumps
    assign j_offset = {{13{idata[31]}},idata[19:12],idata[20],idata[30:21]} << 1;    //JAL ops
    assign j_dest = {{20{immediate[11]}},immediate} + rv1;                           //JALR ops

    //Compute next PC value
    assign iaddr_new = (opflag == 3) ? iaddr + b_offset :                 //Branch
                       (opflag == 6) ? iaddr + j_offset :                 //JAL
                       (opflag == 7) ? {j_dest[31:1],1'b0} : iaddr + 4;   //JALR : Default

    /*--------------------------------------------------------------------------------------------------------------------*/

    //ALU
    assign alu_imm = (func3[1:0] == 2'b01) ? {7'b0,rs2} : immediate;
    assign alu_in1 = rv1;
    assign alu_in2 = (opflag === 2) ? {{20{alu_imm[11]}},alu_imm} : rv2;

    always @(*) begin
        casez ({opcode[5],idata[30],func3})
            5'b0?000 : alu_opcode = 1;      //ADD
            5'b10000 : alu_opcode = 1;      //ADD
            5'b11000 : alu_opcode = 2;      //SUB
            5'b??111 : alu_opcode = 3;      //AND
            5'b??110 : alu_opcode = 4;      //OR
            5'b??100 : alu_opcode = 5;      //XOR
            5'b??010 : alu_opcode = 6;      //SLT
            5'b??011 : alu_opcode = 7;      //SLTU
            5'b??001 : alu_opcode = 8;      //SLL
            5'b?0101 : alu_opcode = 9;      //SRL
            5'b?1101 : alu_opcode = 10;     //SRA
            default  : alu_opcode = 0;      //undefined
        endcase
    end

    /*--------------------------------------------------------------------------------------------------------------------*/

    //Load/Store
    assign u_immediate = {immediate,rs1,func3,12'b0};         //Upper immediate value
    assign s_offset = {idata[31:25],idata[11:7]};             //Offset for store ops
    assign m_offset = (opflag === 8) ? immediate : s_offset;  //Actual offset
    assign daddr = {{20{m_offset[11]}},m_offset} + rv1;       //addr for dmem
    assign mem_addr = (opflag === 8) ? rd : rs2;              //addr for internal registers

    //Handling mis-aligned address cases with a buffer
    assign buff_in = (opflag == 9) ? rv3 :
                     (daddr[1:0] == 2'b00) ? drdata :
                     (daddr[1:0] == 2'b01) ? (drdata >> 8) :
                     (daddr[1:0] == 2'b10) ? (drdata >> 16) :
                     (daddr[1:0] == 2'b11) ? (drdata >>24) : 0;

    always @(buff_in) begin
        case (func3)
            3'b000:   buff_out = {{24{buff_in[7]}},buff_in[7:0]};      //Byte
            3'b001:   buff_out = {{16{buff_in[15]}},buff_in[15:0]};    //Half-Word
            3'b010:   buff_out = buff_in;                              //Word
            3'b100:   buff_out = {24'b0,buff_in[7:0]};                 //Byte-Unsigned
            3'b101:   buff_out = {16'b0,buff_in[15:0]};                //Half-Word-Unsigned
            default:  buff_out = 32'b0;
        endcase             
    end

    //data value for dmem and write enable
    assign dwdata = (daddr[1:0] == 2'b00) ? buff_out :
                    (daddr[1:0] == 2'b01) ? (buff_out << 8) :
                    (daddr[1:0] == 2'b10) ? (buff_out << 16) : 
                    (daddr[1:0] == 2'b11) ? (buff_out << 24) : 0;
    
    assign dwe = (opflag !== 9) ? 0 :
                 (func3 == 3'b000 | func3 == 3'b100) ? {daddr[1] & daddr[0], daddr[1] & !daddr[0], !daddr[1] & daddr[0],!daddr[1] & !daddr[0]} : 
                 (func3 == 3'b001 | func3 == 3'b101) ? {daddr[1], daddr[1], !daddr[1], !daddr[1]} :
                 (func3 == 3'b010) ? 4'b1111 : 4'b0000;

    /*--------------------------------------------------------------------------------------------------------------------*/
    
    //Updating internal registers
    assign reg_we   = (reg_dest !== 0 & opflag !== 3 & opflag !== 9) ? 1 : 0;   //for branch, store, invalid ops, =0 else, =1
    assign reg_dest = (opflag == 8) ? mem_addr : rd;                            //handling load ops separately
    assign reg_data = (opflag == 1 | opflag == 2) ? alu_out :                   //ALU
                      (opflag == 4)               ? u_immediate :               //LUI
                      (opflag == 5)               ? iaddr + u_immediate :       //AUIPC
                      (opflag == 6 | opflag == 7) ? iaddr + 4 :                 //JAL/JALR
                      (opflag == 8)               ? buff_out : 0;               //Load

endmodule

a6 - IO Peripheral/cpu_tb.v
`timescale 1ns/1ns 

// You may need to change the NCYCLES value till the program prints properly
// since we don't know how long the print functions will take
`define NCYCLES 10000

// This test bench will run for a fixed 1000 clock cycles and then dump out the memory
// Test cases are such that they should finish within this time
// If the CPU continues after this point, it should not result in changes in data
// Safe to assume that imem contains only 0 after the last instruction

// MACROS:
// A single parameter is passed into the code, 
// which is the path to the files imem.mem, dmem0-3.mem and expout.mem
// Test cases ensure the files are named appropriately
module cpu_tb ();
    
    reg  clk, reset;
    wire [31:0] iaddr, idata, daddr, drdata, dwdata;
    wire [31:0] daddr1, drdata1, dwdata1;
    wire [31:0] daddr2, drdata2, dwdata2;
    wire [3:0] dwe, dwe1, dwe2;
    integer i, s, fail, log_file, exp_file;
    reg [31:0] dtmp, exp_reg;

    // Instantiate the CPU
    cpu u1(
        .clk(clk),
        .reset(reset),
        .iaddr(iaddr),
        .idata(idata),
        .daddr(daddr),
        .drdata(drdata),
        .dwdata(dwdata),
        .dwe(dwe)
    );

    imem u2(
        .iaddr(iaddr),
        .idata(idata)
    );

    dmem u3(
        .clk(clk),
        .daddr(daddr1),
        .drdata(drdata1),
        .dwdata(dwdata1),
        .dwe(dwe1)
    );

    outperiph u4( 
        .clk(clk),
        .reset(reset),  // Send reset 
        .daddr(daddr2),
        .drdata(drdata2),
        .dwdata(dwdata2),
        .dwe(dwe2)
    );

    biu u5(
        .clk(clk),
        .reset(reset),
        // Interface to CPU
        .daddr(daddr),
        .drdata(drdata),
        .dwdata(dwdata),
        .dwe(dwe),
        // Interface to DMEM
        .daddr1(daddr1),
        .drdata1(drdata1),
        .dwdata1(dwdata1),
        .dwe1(dwe1),
        // Interface to peripheral
        .daddr2(daddr2),
        .drdata2(drdata2),
        .dwdata2(dwdata2),
        .dwe2(dwe2)
    );

    // Set up clock
    always #5 clk=~clk;

    initial begin
	// Uncomment below to dump out VCD file for gtkwave
	// NOTE: This will NOT work on the jupyter terminal
	    $dumpfile("cpu_tb.vcd");
	    $dumpvars;
        $display("RUNNING TEST FROM ", `TESTDIR);
        clk = 1;
        reset = 1;   // This is active high reset
        #100         // At least 100 because Xilinx assumes 100ns reset in post-syn sim
        reset = 0;   // Reset removed - normal functioning resumes
        @(posedge clk);
        for (i=0; i<`NCYCLES; i=i+1) begin
            @(posedge clk);
        end
        
        $finish;
    end

endmodule

a6 - IO Peripheral/cpu_tb.vcd
$date
	Wed Nov 18 08:14:14 2020
$end
$version
	Icarus Verilog
$end
$timescale
	1ps
$end
$scope module cpu_tb $end
$var wire 32 ! idata [31:0] $end
$var wire 32 " iaddr [31:0] $end
$var wire 4 # dwe2 [3:0] $end
$var wire 4 $ dwe1 [3:0] $end
$var wire 4 % dwe [3:0] $end
$var wire 32 & dwdata2 [31:0] $end
$var wire 32 ' dwdata1 [31:0] $end
$var wire 32 ( dwdata [31:0] $end
$var wire 32 ) drdata2 [31:0] $end
$var wire 32 * drdata1 [31:0] $end
$var wire 32 + drdata [31:0] $end
$var wire 32 , daddr2 [31:0] $end
$var wire 32 - daddr1 [31:0] $end
$var wire 32 . daddr [31:0] $end
$var reg 1 / clk $end
$var reg 1 0 reset $end
$var integer 32 1 i [31:0] $end
$scope module u1 $end
$var wire 32 2 alu_in1 [31:0] $end
$var wire 1 / clk $end
$var wire 1 0 reset $end
$var wire 32 3 u_immediate [31:0] $end
$var wire 12 4 s_offset [11:0] $end
$var wire 32 5 rv3 [31:0] $end
$var wire 32 6 rv2 [31:0] $end
$var wire 32 7 rv1 [31:0] $end
$var wire 5 8 rs2 [4:0] $end
$var wire 5 9 rs1 [4:0] $end
$var wire 1 : reg_we $end
$var wire 5 ; reg_dest [4:0] $end
$var wire 32 < reg_data [31:0] $end
$var wire 5 = rd [4:0] $end
$var wire 7 > opcode [6:0] $end
$var wire 5 ? mem_addr [4:0] $end
$var wire 12 @ m_offset [11:0] $end
$var wire 32 A j_offset [31:0] $end
$var wire 32 B j_dest [31:0] $end
$var wire 12 C immediate [11:0] $end
$var wire 32 D idata [31:0] $end
$var wire 32 E iaddr_new [31:0] $end
$var wire 3 F func3 [2:0] $end
$var wire 4 G dwe [3:0] $end
$var wire 32 H dwdata [31:0] $end
$var wire 32 I drdata [31:0] $end
$var wire 32 J daddr [31:0] $end
$var wire 32 K buff_in [31:0] $end
$var wire 32 L b_offset [31:0] $end
$var wire 32 M b_imm [31:0] $end
$var wire 32 N alu_out [31:0] $end
$var wire 32 O alu_in2 [31:0] $end
$var wire 12 P alu_imm [11:0] $end
$var reg 6 Q alu_opcode [5:0] $end
$var reg 32 R buff_out [31:0] $end
$var reg 32 S iaddr [31:0] $end
$var reg 5 T opflag [4:0] $end
$scope module i1 $end
$var wire 6 U op [5:0] $end
$var wire 32 V rv1 [31:0] $end
$var wire 32 W rv2 [31:0] $end
$var wire 32 X rvout [31:0] $end
$var reg 32 Y alu_out [31:0] $end
$upscope $end
$scope module i2 $end
$var wire 1 / clk $end
$var wire 5 Z rd [4:0] $end
$var wire 5 [ rs1 [4:0] $end
$var wire 5 \ rs2 [4:0] $end
$var wire 5 ] rs3 [4:0] $end
$var wire 32 ^ rv1 [31:0] $end
$var wire 32 _ rv2 [31:0] $end
$var wire 32 ` rv3 [31:0] $end
$var wire 32 a wdata [31:0] $end
$var wire 1 b we $end
$var integer 32 c i [31:0] $end
$upscope $end
$upscope $end
$scope module u2 $end
$var wire 32 d iaddr [31:0] $end
$var wire 32 e idata [31:0] $end
$upscope $end
$scope module u3 $end
$var wire 1 / clk $end
$var wire 4 f dwe [3:0] $end
$var wire 32 g dwdata [31:0] $end
$var wire 32 h drdata [31:0] $end
$var wire 32 i daddr [31:0] $end
$var wire 30 j a [29:0] $end
$var integer 32 k i [31:0] $end
$upscope $end
$scope module u4 $end
$var wire 1 / clk $end
$var wire 1 0 reset $end
$var wire 4 l dwe [3:0] $end
$var wire 32 m dwdata [31:0] $end
$var wire 32 n daddr [31:0] $end
$var reg 32 o drdata [31:0] $end
$var integer 32 p out_file [31:0] $end
$upscope $end
$scope module u5 $end
$var wire 1 / clk $end
$var wire 32 q daddr [31:0] $end
$var wire 32 r daddr1 [31:0] $end
$var wire 32 s daddr2 [31:0] $end
$var wire 32 t drdata1 [31:0] $end
$var wire 32 u drdata2 [31:0] $end
$var wire 32 v dwdata [31:0] $end
$var wire 32 w dwdata1 [31:0] $end
$var wire 32 x dwdata2 [31:0] $end
$var wire 4 y dwe [3:0] $end
$var wire 1 0 reset $end
$var wire 4 z dwe2 [3:0] $end
$var wire 4 { dwe1 [3:0] $end
$var wire 32 | drdata [31:0] $end
$upscope $end
$upscope $end
$enddefinitions $end
#0
$dumpvars
b10000110010111 |
b0 {
b0 z
b0 y
b0 x
b0 w
b0 v
b0 u
b10000110010111 t
b11 s
b11 r
b11 q
b10000000000000000000000000000011 p
b0 o
b11 n
b0 m
b0 l
b100101000100 k
b0 j
b11 i
b10000110010111 h
b0 g
b0 f
b10000110010111 e
b0 d
b100000 c
0b
b10000000000000 a
b0 `
b0 _
b0 ^
b0 ]
b0 \
b0 [
b11 Z
b0 Y
b0 X
b0 W
b0 V
b110 U
b101 T
b0 S
b0 R
b110 Q
b0 P
b0 O
b0 N
b100000000010 M
b100 L
b0 K
b11 J
b10000110010111 I
b0 H
b0 G
b10 F
b100 E
b10000110010111 D
b0 C
b0 B
b10000000000000 A
b11 @
b0 ?
b10111 >
b11 =
b10000000000000 <
b11 ;
1:
b0 9
b0 8
b0 7
b0 6
b0 5
b11 4
b10000000000000 3
b0 2
bx 1
10
1/
b11 .
b11 -
b11 ,
b10000110010111 +
b10000110010111 *
b0 )
b0 (
b0 '
b0 &
b0 %
b0 $
b0 #
b0 "
b10000110010111 !
$end
#5000
0/
#10000
1/
#15000
0/
#20000
1/
#25000
0/
#30000
1/
#35000
0/
#40000
1/
#45000
0/
#50000
1/
#55000
0/
#60000
1/
#65000
0/
#70000
1/
#75000
0/
#80000
1/
#85000
0/
#90000
1/
#95000
0/
#100000
b10000000000000 2
b10000000000000 V
b10000000000000 7
b10000000000000 ^
bx000000000000000000000000 '
bx000000000000000000000000 g
bx000000000000000000000000 w
bx000000000000000000000000 &
bx000000000000000000000000 m
bx000000000000000000000000 x
bx000000000000000000000000 (
bx000000000000000000000000 H
bx000000000000000000000000 v
bx R
b0xxxxxxxx K
bx +
bx I
bx |
b1101110011000 N
b1101110011000 X
b1101110011000 Y
bx *
bx h
bx t
b11011100000 j
b11111111111111111111101110011000 O
b11111111111111111111101110011000 W
b100 L
b1000 E
b1101110011000 <
b1101110011000 a
b1101110000011 -
b1101110000011 i
b1101110000011 r
b1101110000011 ,
b1101110000011 n
b1101110000011 s
b1101110000011 .
b1101110000011 J
b1101110000011 q
b101110000011 @
b11111111111100011000001110011000 A
b11111111111111111111101110000010 M
b10 T
b1 Q
b1 U
b11000 ?
b11000 ]
b101110011000 P
b101110000011 4
b10011 >
b0 F
b11 9
b11 [
b11000 8
b11000 \
b1101110011000 B
b10111001100000011000000000000000 3
b101110011000 C
b10111001100000011000000110010011 !
b10111001100000011000000110010011 D
b10111001100000011000000110010011 e
b100 "
b100 S
b100 d
b0 1
1b
1/
00
#105000
0/
#110000
b0 R
b0 K
b0 '
b0 g
b0 w
b0 &
b0 m
b0 x
b0 (
b0 H
b0 v
b10000110010111 *
b10000110010111 h
b10000110010111 t
b10000110010111 +
b10000110010111 I
b10000110010111 |
b1000000001000 <
b1000000001000 a
b0 O
b0 W
b1100 E
b10 @
b1000000000000 A
b10 M
b101 T
b10 ;
b10 Z
b1000 Q
b1000 U
b0 j
b0 N
b0 X
b0 Y
b0 ?
b0 ]
b0 P
b10 4
b10111 >
b10 =
b1 F
b10 -
b10 i
b10 r
b10 ,
b10 n
b10 s
b10 .
b10 J
b10 q
b0 2
b0 V
b0 7
b0 ^
b0 9
b0 [
b0 8
b0 \
b0 B
b1000000000000 3
b0 C
b1000100010111 !
b1000100010111 D
b1000100010111 e
b1 1
b1000 "
b1000 S
b1000 d
1/
#115000
0/
#120000
b1000000001000 2
b1000000001000 V
b1000000001000 7
b1000000001000 ^
bx0000000000000000 '
bx0000000000000000 g
bx0000000000000000 w
bx0000000000000000 &
bx0000000000000000 m
bx0000000000000000 x
bx0000000000000000 (
bx0000000000000000 H
bx0000000000000000 v
bx R
b0xxxxxxxxxxxxxxxx K
bx +
bx I
bx |
b1000000000000 N
b1000000000000 X
b1000000000000 Y
bx *
bx h
bx t
b1111111010 j
b11111111111111111111111111111000 O
b11111111111111111111111111111000 W
b100 L
b10000 E
b1000000000000 <
b1000000000000 a
b111111101010 -
b111111101010 i
b111111101010 r
b111111101010 ,
b111111101010 n
b111111101010 s
b111111101010 .
b111111101010 J
b111111101010 q
b111111100010 @
b11111111111100010000011111111000 A
b11111111111111111111011111100010 M
b10 T
b1 Q
b1 U
b111111111000 P
b11000 ?
b11000 ]
b111111100010 4
b10011 >
b0 F
b10 9
b10 [
b11000 8
b11000 \
b1000000000000 B
b11111111100000010000000000000000 3
b111111111000 C
b11111111100000010000000100010011 !
b11111111100000010000000100010011 D
b11111111100000010000000100010011 e
b1100 "
b1100 S
b1100 d
b10 1
1/
#125000
0/
#130000
b1000000000000 2
b1000000000000 V
b1000000000000 7
b1000000000000 ^
bx R
bx K
b1000000000000 <
b1000000000000 a
bx '
bx g
bx w
bx &
bx m
bx x
bx (
bx H
bx v
bx +
bx I
bx |
b1000000000000 N
b1000000000000 X
b1000000000000 Y
bx *
bx h
bx t
b10000000010 j
b0 O
b0 W
b10100 E
b1000000001000 -
b1000000001000 i
b1000000001000 r
b1000000001000 ,
b1000000001000 n
b1000000001000 s
b1000000001000 .
b1000000001000 J
b1000000001000 q
b1000 @
b10000000000000000 A
b1000 M
b1 T
b1000 ;
b1000 Z
b0 ?
b0 ]
b0 P
b1000 4
b110011 >
b1000 =
b0 8
b0 \
b1000000000000 B
b10000000000000000 3
b0 C
b10000010000110011 !
b10000010000110011 D
b10000010000110011 e
b11 1
b10000 "
b10000 S
b10000 d
1/
#135000
0/
#140000
0b
b11111111111111111111111110000011 '
b11111111111111111111111110000011 g
b11111111111111111111111110000011 w
b11111111111111111111111110000011 &
b11111111111111111111111110000011 m
b11111111111111111111111110000011 x
b11111111111111111111111110000011 (
b11111111111111111111111110000011 H
b11111111111111111111111110000011 v
0:
b11111111111111111111111110000011 R
b1110000010010000010000011 K
b1110000010010000010000011 +
b1110000010010000010000011 I
b1110000010010000010000011 |
b1100000000 L
b11000 <
b11000 a
b1100010100 E
b1100000000 @
b1100000000 A
b1100000000 M
b110 T
b0 ;
b0 Z
b1110000010010000010000011 *
b1110000010010000010000011 h
b1110000010010000010000011 t
b11000000 j
b0 N
b0 X
b0 Y
b1100000000 P
b1100000000 4
b1101111 >
b0 =
b1100000000 -
b1100000000 i
b1100000000 r
b1100000000 ,
b1100000000 n
b1100000000 s
b1100000000 .
b1100000000 J
b1100000000 q
b0 2
b0 V
b0 7
b0 ^
b0 9
b0 [
b1100000000 B
b110000000000000000000000000000 3
b1100000000 C
b110000000000000000000001101111 !
b110000000000000000000001101111 D
b110000000000000000000001101111 e
b10100 "
b10100 S
b10100 d
b100 1
1/
#145000
0/
#150000
1b
1:
bx R
b0xxxxxxxxxxxxxxxx K
bx0000000000000000 '
bx0000000000000000 g
bx0000000000000000 w
bx0000000000000000 &
bx0000000000000000 m
bx0000000000000000 x
bx0000000000000000 (
bx0000000000000000 H
bx0000000000000000 v
b111111110000 <
b111111110000 a
b11111111111111111111111111110000 O
b11111111111111111111111111110000 W
bx +
bx I
bx |
b100 L
b111111100010 @
b11111111111100010000011111110000 A
b11111111111111111111011111100010 M
b10 T
b10 ;
b10 Z
bx *
bx h
bx t
b1111111000 j
b10000 ?
b10000 ]
b111111110000 P
b111111110000 N
b111111110000 X
b111111110000 Y
b1100011000 E
b111111100010 4
b10011 >
b10 =
b111111100010 -
b111111100010 i
b111111100010 r
b111111100010 ,
b111111100010 n
b111111100010 s
b111111100010 .
b111111100010 J
b111111100010 q
b1000000000000 2
b1000000000000 V
b1000000000000 7
b1000000000000 ^
b10 9
b10 [
b10000 8
b10000 \
b111111110000 B
b11111111000000010000000000000000 3
b111111110000 C
b1 Q
b1 U
b11111111000000010000000100010011 !
b11111111000000010000000100010011 D
b11111111000000010000000100010011 e
b101 1
b1100010100 "
b1100010100 S
b1100010100 d
1/
#155000
0/
#160000
b111111110000 2
b111111110000 V
b111111110000 7
b111111110000 ^
0b
0:
b0 '
b0 g
b0 w
b0 &
b0 m
b0 x
b0 (
b0 H
b0 v
bx +
bx I
bx |
b0 R
b1111 $
b1111 f
b1111 {
b0 <
b0 a
bx *
bx h
bx t
b1111111111 j
b0 K
b1111 %
b1111 G
b1111 y
b0 N
b0 X
b0 Y
b0 O
b0 W
b1100011100 E
b111111111100 -
b111111111100 i
b111111111100 r
b111111111100 ,
b111111111100 n
b111111111100 s
b111111111100 .
b111111111100 J
b111111111100 q
b1100 @
b10010100000000000 A
b1100 M
b1001 T
b1100 ;
b1100 Z
b110 Q
b110 U
b1 ?
b1 ]
b1 P
b1100 4
b100011 >
b1100 =
b10 F
b1 8
b1 \
b111111110001 B
b100010010000000000000 3
b1 C
b100010010011000100011 !
b100010010011000100011 D
b100010010011000100011 e
b1100011000 "
b1100011000 S
b1100011000 d
b110 1
1/
#165000
0/
#170000
b1000000000000 '
b1000000000000 g
b1000000000000 w
b1000000000000 &
b1000000000000 m
b1000000000000 x
b1000000000000 (
b1000000000000 H
b1000000000000 v
b1000000000000 R
b1111111110 j
b1000000000000 K
b1 N
b1 X
b1 Y
b1100100000 E
b111111111000 -
b111111111000 i
b111111111000 r
b111111111000 ,
b111111111000 n
b111111111000 s
b111111111000 .
b111111111000 J
b111111111000 q
b1000 @
b10010000000001000 A
b1000 M
b1000 ;
b1000 Z
b1000000000000 5
b1000000000000 `
b1000 ?
b1000 ]
b1000000000000 O
b1000000000000 W
b1000 P
b1000 4
b1000 =
b1000000000000 6
b1000000000000 _
b1000 8
b1000 \
b111111111000 B
b100000010010000000000000 3
b1000 C
bx +
bx I
bx |
b100000010010010000100011 !
b100000010010010000100011 D
b100000010010010000100011 e
b111 1
bx *
bx h
bx t
b1100011100 "
b1100011100 S
b1100011100 d
1/
#175000
0/
